README.md
setup.py
emblem/__init__.py
emblem/__main__.py
emblem/emblem.py
emblem/utilities.py
emblem.egg-info/PKG-INFO
emblem.egg-info/SOURCES.txt
emblem.egg-info/dependency_links.txt
emblem.egg-info/entry_points.txt
emblem.egg-info/requires.txt
emblem.egg-info/top_level.txt