Metadata-Version: 2.1
Name: emblem
Version: 1.0.4
Summary: shields.io + colormaps
Home-page: https://github.com/alopezrivera/emblem
Author: Antonio Lopez Rivera
Author-email: antonlopezr99@gmail.com
License: UNKNOWN
Platform: UNKNOWN
Classifier: Programming Language :: Python :: 3
Classifier: License :: OSI Approved :: GNU General Public License v3 (GPLv3)
Classifier: Operating System :: OS Independent
Requires-Python: >=3.6
